README.md
setup.cfg
setup.py
epm/__init__.py
epm/api.py
epm/enums.py
epm/errors.py
epm/main.py
epm/requirements.txt
epm/requirements_dev.txt
epm/requirements_osx.txt
epm/requirements_server.txt
epm.egg-info/PKG-INFO
epm.egg-info/SOURCES.txt
epm.egg-info/dependency_links.txt
epm.egg-info/entry_points.txt
epm.egg-info/requires.txt
epm.egg-info/top_level.txt
epm/client/__init__.py
epm/client/command.py
epm/client/output.py
epm/client/userio.py
epm/client/commands/__init__.py
epm/client/commands/build.py
epm/client/commands/create.py
epm/client/commands/gitlab-runner.py
epm/client/commands/init.py
epm/client/commands/mkdocs.py
epm/client/commands/runit.py
epm/client/commands/sandbox.py
epm/client/commands/upload.py
epm/client/commands/venv.py
epm/client/conf/__init__.py
epm/client/conf/config_installer.py
epm/client/conf/detect.py
epm/client/tools/__init__.py
epm/client/tools/env.py
epm/client/tools/project.py
epm/client/tools/venv.py
epm/data/project/cmake/CMakeLists.txt
epm/data/project/cmake/config.cmake.in
epm/data/project/cmake/libCMakeLists.txt
epm/data/project/docs/index.md
epm/data/project/docs/mkdocs.yml
epm/data/project/docs/release-notes.md
epm/data/project/docs/user-guide.md
epm/data/project/include/declaration.h
epm/data/project/include/lib.h
epm/data/project/script/gitlab-ci.py
epm/data/project/script/gitlab-ci2.py
epm/data/project/source/lib.c
epm/data/project/source/main.c
epm/data/project/test_package/CMakeLists.txt
epm/data/project/test_package/app-conanfile.py
epm/data/project/test_package/conanfile.py
epm/data/project/test_package/main.cpp
epm/data/project/test_package/main.py
epm/data/project/test_package/test.cpp
epm/data/project/test_package/test_version.py
epm/model/__init__.py
epm/model/configuration.py
epm/model/env_info.py
epm/model/environment.py
epm/model/profile.py
epm/model/project.py
epm/model/register.py
epm/model/sandbox.py
epm/model/scheme.py
epm/paths/__init__.py
epm/paths/location.py
epm/utils/__init__.py
epm/utils/config_parser.py
epm/utils/docker.py
epm/utils/env_reader.py
epm/utils/files.py
epm/utils/log.py
epm/utils/shell.py
epm/utils/ssh.py
epm/utils/tracer.py
epm/utils/windows.py
