Metadata-Version: 2.1
Name: epm
Version: 0.0.57
Summary: Enterprise package management for C/C++ development base on conan
Home-page: https://epmall.github.io/epm
Author: Mingyi Zhang
Author-email: mingyi.z@outlook.com
License: MIT
Keywords: C/C++,package,libraries,developer,manager,dependency,tool,c,c++,cpp
Platform: UNKNOWN
Classifier: Development Status :: 1 - Planning
Classifier: Intended Audience :: Developers
Classifier: Topic :: Software Development :: Build Tools
Classifier: License :: OSI Approved :: MIT License
Classifier: Programming Language :: Python :: 3
Classifier: Programming Language :: Python :: 3.6
Provides-Extra: test
Provides-Extra: dev
